embed_lab/__init__.py
embed_lab/cli.py
embed_lab-0.5.0.dist-info/WHEEL
embed_lab-0.5.0.dist-info/entry_points.txt
embed_lab-0.5.0.dist-info/METADATA
embed_lab-0.5.0.dist-info/RECORD
