Metadata-Version: 2.3
Name: embed_lab
Version: 0.5.0
Summary: Add your description here
Author: mohamad-tohidi
Author-email: mohamad-tohidi <the.mohammad.tohidi@gmail.com>
Requires-Dist: pydantic>=2.12.5
Requires-Dist: textual>=7.5.0
Requires-Dist: typer>=0.21.1
Requires-Python: >=3.12
